{
    "animals": [
        {
            "id": 1,
            "name": "Doodles",
            "breed": "Poodle",
            "customerId": 1,
            "locationId": 2
        },
        {
            "id": 2,
            "name": "Chico",
            "breed": "barkydog",
            "customerId": 2,
            "locationId": 1
        },
        {
            "id": 3,
            "name": "Killer",
            "breed": "Shitzu",
            "customerId": 3,
            "locationId": 1
        }
    ],
    "customers": [
        {
            "id": 1,
            "name": "Hannah Hall",
            "address": "7002 Chestnut Ct"
        },
        {
            "id": 2,
            "name": "Dalton Tall",
            "address": "102 Lake Rd"
        },
        {
            "id": 3,
            "name": "Darren Ball",
            "address": "99 Swiss Ln"
        }
    ],
    "employees": [
        {
            "id": 1,
            "name": "Jeremy Bakker",
            "locationId": 2
        },
        {
            "id": 2,
            "name": "Tanya Rene",
            "locationId": 1
        },
        {
            "id": 3,
            "name": "Kayla Gill",
            "locationId": 2
        },
        {
            "id": 4,
            "name": "Jeff Coly",
            "locationId": 1
        }
    ],
    "locations": [
        {
            "id": 1,
            "name": "Nashville North",
            "address": "8422 Johnson Pike"
        },
        {
            "id": 2,
            "name": "Nashville South",
            "address": "209 Emory Drive"
        },
        {
            "id": 3,
            "name": "Nashville East",
            "address": "505 Gallatin Pike"
        }
    ]
}
